{"uk":{"name":"tick","examples":[],"description":"","bemjsonDescription":""},"ru":{"name":"tick","examples":[],"description":"<h1 id=\"tick\"><a href=\"#tick\" class=\"anchor\"></a>tick</h1>\n<p>Блок предоставляет объект для работы с регулярно генерируемым событием <code>tick</code> (для реализации паттерна polling).</p>\n<h2 id=\"Обзор-13\"><a href=\"#Обзор-13\" class=\"anchor\"></a>Обзор</h2>\n<h3 id=\"События-объекта-2\"><a href=\"#События-объекта-2\" class=\"anchor\"></a>События объекта</h3>\n<div class=\"table-container\"><table>\n<thead>\n<tr>\n<th>Имя</th>\n<th>Описание</th>\n</tr>\n</thead>\n<tbody>\n<tr>\n<td><a href=\"#events-tick\">tick</a></td>\n<td>Регулярно генерируемое событие.</td>\n</tr>\n</tbody>\n</table>\n</div><h3 id=\"Свойства-и-методы-объекта-13\"><a href=\"#Свойства-и-методы-объекта-13\" class=\"anchor\"></a>Свойства и методы объекта</h3>\n<div class=\"table-container\"><table>\n<thead>\n<tr>\n<th>Имя</th>\n<th>Тп возвращаемого значения</th>\n<th>Описание</th>\n</tr>\n</thead>\n<tbody>\n<tr>\n<td><a href=\"#fields-start\">start</a>()</td>\n<td>-</td>\n<td>Запускает генерацию события <code>tick</code>, если она еще не запущена.</td>\n</tr>\n<tr>\n<td><a href=\"#fields-stop\">stop</a>()</td>\n<td>-</td>\n<td>Останавливает генерацию события <code>tick</code>, если она еще не остановлена.</td>\n</tr>\n</tbody>\n</table>\n</div><h3 id=\"Модификаторы-блока-4\"><a href=\"#Модификаторы-блока-4\" class=\"anchor\"></a>Модификаторы блока</h3>\n<div class=\"table-container\"><table>\n<thead>\n<tr>\n<th>Модификатор</th>\n<th>Допустимые значения</th>\n<th>Способы использования</th>\n<th>Описание</th>\n</tr>\n</thead>\n<tbody>\n<tr>\n<td><a href=\"#modifiers-start\">start</a></td>\n<td><code>&#39;auto&#39;</code></td>\n<td><code>JS</code></td>\n<td>Автоматический запуск генерации события</td>\n</tr>\n</tbody>\n</table>\n</div><h3 id=\"Публичные-технологии-блока-16\"><a href=\"#Публичные-технологии-блока-16\" class=\"anchor\"></a>Публичные технологии блока</h3>\n<p>Блок реализован в технологиях:</p>\n<ul>\n<li><code>vanilla.js</code></li>\n</ul>\n<h2 id=\"Описание-11\"><a href=\"#Описание-11\" class=\"anchor\"></a>Описание</h2>\n<p><a name=\"events\"></a></p>\n<h3 id=\"События-объекта-3\"><a href=\"#События-объекта-3\" class=\"anchor\"></a>События объекта</h3>\n<p><a name=\"events-tick\"></a></p>\n<h4 id=\"Событие-tick\"><a href=\"#Событие-tick\" class=\"anchor\"></a>Событие <code>tick</code></h4>\n<p>Подписавшись на событие, можно использовать его для реализации паттерна polling.</p>\n<p>Событие генерируется с интервалом в 50 миллисекунд.</p>\n<p><a name=\"fields\"></a></p>\n<h3 id=\"Свойства-и-методы-объекта-14\"><a href=\"#Свойства-и-методы-объекта-14\" class=\"anchor\"></a>Свойства и методы объекта</h3>\n<p>Блок наследуется от клсаса <code>Emitter</code> блока <code>events</code>, что позволяет вызывать методы класса.</p>\n<pre><code class=\"lang-js\">modules.require(&#39;tick&#39;, function(tick) {\n\nvar update = function() { /* ... */ };\n\ntick\n    .on(&#39;tick&#39;, update) // подписываемся на событие tick\n    .start(); // запускаем генерацию события tick\n});\n</code></pre>\n<p><a name=\"fields-start\"></a></p>\n<h4 id=\"Метод-start-1\"><a href=\"#Метод-start-1\" class=\"anchor\"></a>Метод <code>start</code></h4>\n<p>Запускает генерацию события <a href=\"#fields-tick\">tick</a>, если они еще не запущены. Событие <code>tick</code> генерируется через интервал в 50 миллисекунд после вызова метода.</p>\n<p>Не принимает аргументов.</p>\n<p>Не имеет возвращаемого значения.</p>\n<p><a name=\"fields-stop\"></a></p>\n<h4 id=\"Метод-stop-1\"><a href=\"#Метод-stop-1\" class=\"anchor\"></a>Метод <code>stop</code></h4>\n<p>Останавливает генерацию события <a href=\"#fields-tick\">tick</a>.</p>\n<p>Не принимает аргументов.</p>\n<p>Не имеет возвращаемого значения.</p>\n<p><a name=\"modifiers\"></a></p>\n<h3 id=\"Модификаторы-блока-5\"><a href=\"#Модификаторы-блока-5\" class=\"anchor\"></a>Модификаторы блока</h3>\n<p><a name=\"modifiers-start\"></a></p>\n<h4 id=\"Модификатор-start-1\"><a href=\"#Модификатор-start-1\" class=\"anchor\"></a>Модификатор <code>start</code></h4>\n<p>Допустимые значения: <code>&#39;auto&#39;</code>.</p>\n<p>Способ использования: <code>JS</code>.</p>\n<p>Блок с модификатором <code>start</code> в значении <code>auto</code> используется для автоматического запуска генерации события <a href=\"#fields-tick\">tick</a>. Событие начинает генерироваться в момент инициализации блока.</p>\n","bemjsonDescription":"{\n    \"block\": \"md-root\",\n    \"content\": [\n        {\n            \"level\": 1,\n            \"block\": \"heading\",\n            \"mods\": {\n                \"level\": 1\n            },\n            \"content\": \"tick\"\n        },\n        {\n            \"block\": \"paragraph\",\n            \"content\": [\n                \"Блок предоставляет объект для работы с регулярно генерируемым событием \",\n                {\n                    \"block\": \"inline-code\",\n                    \"content\": \"tick\"\n                },\n                \" (для реализации паттерна polling).\"\n            ]\n        },\n        {\n            \"level\": 2,\n            \"block\": \"heading\",\n            \"mods\": {\n                \"level\": 2\n            },\n            \"content\": \"Обзор\"\n        },\n        {\n            \"level\": 3,\n            \"block\": \"heading\",\n            \"mods\": {\n                \"level\": 3\n            },\n            \"content\": \"События объекта\"\n        },\n        {\n            \"align\": [\n                null,\n                null\n            ],\n            \"block\": \"table\",\n            \"rows\": [\n                [\n                    \"Имя\",\n                    \"Описание\"\n                ],\n                [\n                    [\n                        {\n                            \"block\": \"html\",\n                            \"content\": \"<a href=\\\"#events-tick\\\">\"\n                        },\n                        \"tick\",\n                        {\n                            \"block\": \"html\",\n                            \"content\": \"</a>\"\n                        }\n                    ],\n                    \"Регулярно генерируемое событие.\"\n                ]\n            ]\n        },\n        {\n            \"level\": 3,\n            \"block\": \"heading\",\n            \"mods\": {\n                \"level\": 3\n            },\n            \"content\": \"Свойства и методы объекта\"\n        },\n        {\n            \"align\": [\n                null,\n                null,\n                null\n            ],\n            \"block\": \"table\",\n            \"rows\": [\n                [\n                    \"Имя\",\n                    \"Тп возвращаемого значения\",\n                    \"Описание\"\n                ],\n                [\n                    [\n                        {\n                            \"block\": \"html\",\n                            \"content\": \"<a href=\\\"#fields-start\\\">\"\n                        },\n                        \"start\",\n                        {\n                            \"block\": \"html\",\n                            \"content\": \"</a>\"\n                        },\n                        \"()\"\n                    ],\n                    \"-\",\n                    [\n                        \"Запускает генерацию события \",\n                        {\n                            \"block\": \"inline-code\",\n                            \"content\": \"tick\"\n                        },\n                        \", если она еще не запущена.\"\n                    ]\n                ],\n                [\n                    [\n                        {\n                            \"block\": \"html\",\n                            \"content\": \"<a href=\\\"#fields-stop\\\">\"\n                        },\n                        \"stop\",\n                        {\n                            \"block\": \"html\",\n                            \"content\": \"</a>\"\n                        },\n                        \"()\"\n                    ],\n                    \"-\",\n                    [\n                        \"Останавливает генерацию события \",\n                        {\n                            \"block\": \"inline-code\",\n                            \"content\": \"tick\"\n                        },\n                        \", если она еще не остановлена.\"\n                    ]\n                ]\n            ]\n        },\n        {\n            \"level\": 3,\n            \"block\": \"heading\",\n            \"mods\": {\n                \"level\": 3\n            },\n            \"content\": \"Модификаторы блока\"\n        },\n        {\n            \"align\": [\n                null,\n                null,\n                null,\n                null\n            ],\n            \"block\": \"table\",\n            \"rows\": [\n                [\n                    \"Модификатор\",\n                    \"Допустимые значения\",\n                    \"Способы использования\",\n                    \"Описание\"\n                ],\n                [\n                    [\n                        {\n                            \"block\": \"html\",\n                            \"content\": \"<a href=\\\"#modifiers-start\\\">\"\n                        },\n                        \"start\",\n                        {\n                            \"block\": \"html\",\n                            \"content\": \"</a>\"\n                        }\n                    ],\n                    {\n                        \"block\": \"inline-code\",\n                        \"content\": \"'auto'\"\n                    },\n                    {\n                        \"block\": \"inline-code\",\n                        \"content\": \"JS\"\n                    },\n                    \"Автоматический запуск генерации события\"\n                ]\n            ]\n        },\n        {\n            \"level\": 3,\n            \"block\": \"heading\",\n            \"mods\": {\n                \"level\": 3\n            },\n            \"content\": \"Публичные технологии блока\"\n        },\n        {\n            \"block\": \"paragraph\",\n            \"content\": \"Блок реализован в технологиях:\"\n        },\n        {\n            \"ordered\": false,\n            \"loose\": false,\n            \"block\": \"list\",\n            \"content\": {\n                \"loose\": false,\n                \"checked\": null,\n                \"block\": \"list-item\",\n                \"content\": {\n                    \"block\": \"paragraph\",\n                    \"content\": {\n                        \"block\": \"inline-code\",\n                        \"content\": \"vanilla.js\"\n                    }\n                }\n            }\n        },\n        {\n            \"level\": 2,\n            \"block\": \"heading\",\n            \"mods\": {\n                \"level\": 2\n            },\n            \"content\": \"Описание\"\n        },\n        {\n            \"block\": \"paragraph\",\n            \"content\": [\n                {\n                    \"block\": \"html\",\n                    \"content\": \"<a name=\\\"events\\\">\"\n                },\n                {\n                    \"block\": \"html\",\n                    \"content\": \"</a>\"\n                }\n            ]\n        },\n        {\n            \"level\": 3,\n            \"block\": \"heading\",\n            \"mods\": {\n                \"level\": 3\n            },\n            \"content\": \"События объекта\"\n        },\n        {\n            \"block\": \"paragraph\",\n            \"content\": [\n                {\n                    \"block\": \"html\",\n                    \"content\": \"<a name=\\\"events-tick\\\">\"\n                },\n                {\n                    \"block\": \"html\",\n                    \"content\": \"</a>\"\n                }\n            ]\n        },\n        {\n            \"level\": 4,\n            \"block\": \"heading\",\n            \"mods\": {\n                \"level\": 4\n            },\n            \"content\": [\n                \"Событие \",\n                {\n                    \"block\": \"inline-code\",\n                    \"content\": \"tick\"\n                }\n            ]\n        },\n        {\n            \"block\": \"paragraph\",\n            \"content\": \"Подписавшись на событие, можно использовать его для реализации паттерна polling.\"\n        },\n        {\n            \"block\": \"paragraph\",\n            \"content\": \"Событие генерируется с интервалом в 50 миллисекунд.\"\n        },\n        {\n            \"block\": \"paragraph\",\n            \"content\": [\n                {\n                    \"block\": \"html\",\n                    \"content\": \"<a name=\\\"fields\\\">\"\n                },\n                {\n                    \"block\": \"html\",\n                    \"content\": \"</a>\"\n                }\n            ]\n        },\n        {\n            \"level\": 3,\n            \"block\": \"heading\",\n            \"mods\": {\n                \"level\": 3\n            },\n            \"content\": \"Свойства и методы объекта\"\n        },\n        {\n            \"block\": \"paragraph\",\n            \"content\": [\n                \"Блок наследуется от клсаса \",\n                {\n                    \"block\": \"inline-code\",\n                    \"content\": \"Emitter\"\n                },\n                \" блока \",\n                {\n                    \"block\": \"inline-code\",\n                    \"content\": \"events\"\n                },\n                \", что позволяет вызывать методы класса.\"\n            ]\n        },\n        {\n            \"lang\": \"js\",\n            \"block\": \"code\",\n            \"content\": \"modules.require('tick', function(tick) {\\n\\nvar update = function() { /* ... */ };\\n\\ntick\\n    .on('tick', update) // подписываемся на событие tick\\n    .start(); // запускаем генерацию события tick\\n});\\n\"\n        },\n        {\n            \"block\": \"paragraph\",\n            \"content\": [\n                {\n                    \"block\": \"html\",\n                    \"content\": \"<a name=\\\"fields-start\\\">\"\n                },\n                {\n                    \"block\": \"html\",\n                    \"content\": \"</a>\"\n                }\n            ]\n        },\n        {\n            \"level\": 4,\n            \"block\": \"heading\",\n            \"mods\": {\n                \"level\": 4\n            },\n            \"content\": [\n                \"Метод \",\n                {\n                    \"block\": \"inline-code\",\n                    \"content\": \"start\"\n                }\n            ]\n        },\n        {\n            \"block\": \"paragraph\",\n            \"content\": [\n                \"Запускает генерацию события \",\n                {\n                    \"href\": \"#fields-tick\",\n                    \"block\": \"link\",\n                    \"content\": \"tick\"\n                },\n                \", если они еще не запущены. Событие \",\n                {\n                    \"block\": \"inline-code\",\n                    \"content\": \"tick\"\n                },\n                \" генерируется через интервал в 50 миллисекунд после вызова метода.\"\n            ]\n        },\n        {\n            \"block\": \"paragraph\",\n            \"content\": \"Не принимает аргументов.\"\n        },\n        {\n            \"block\": \"paragraph\",\n            \"content\": \"Не имеет возвращаемого значения.\"\n        },\n        {\n            \"block\": \"paragraph\",\n            \"content\": [\n                {\n                    \"block\": \"html\",\n                    \"content\": \"<a name=\\\"fields-stop\\\">\"\n                },\n                {\n                    \"block\": \"html\",\n                    \"content\": \"</a>\"\n                }\n            ]\n        },\n        {\n            \"level\": 4,\n            \"block\": \"heading\",\n            \"mods\": {\n                \"level\": 4\n            },\n            \"content\": [\n                \"Метод \",\n                {\n                    \"block\": \"inline-code\",\n                    \"content\": \"stop\"\n                }\n            ]\n        },\n        {\n            \"block\": \"paragraph\",\n            \"content\": [\n                \"Останавливает генерацию события \",\n                {\n                    \"href\": \"#fields-tick\",\n                    \"block\": \"link\",\n                    \"content\": \"tick\"\n                },\n                \".\"\n            ]\n        },\n        {\n            \"block\": \"paragraph\",\n            \"content\": \"Не принимает аргументов.\"\n        },\n        {\n            \"block\": \"paragraph\",\n            \"content\": \"Не имеет возвращаемого значения.\"\n        },\n        {\n            \"block\": \"paragraph\",\n            \"content\": [\n                {\n                    \"block\": \"html\",\n                    \"content\": \"<a name=\\\"modifiers\\\">\"\n                },\n                {\n                    \"block\": \"html\",\n                    \"content\": \"</a>\"\n                }\n            ]\n        },\n        {\n            \"level\": 3,\n            \"block\": \"heading\",\n            \"mods\": {\n                \"level\": 3\n            },\n            \"content\": \"Модификаторы блока\"\n        },\n        {\n            \"block\": \"paragraph\",\n            \"content\": [\n                {\n                    \"block\": \"html\",\n                    \"content\": \"<a name=\\\"modifiers-start\\\">\"\n                },\n                {\n                    \"block\": \"html\",\n                    \"content\": \"</a>\"\n                }\n            ]\n        },\n        {\n            \"level\": 4,\n            \"block\": \"heading\",\n            \"mods\": {\n                \"level\": 4\n            },\n            \"content\": [\n                \"Модификатор \",\n                {\n                    \"block\": \"inline-code\",\n                    \"content\": \"start\"\n                }\n            ]\n        },\n        {\n            \"block\": \"paragraph\",\n            \"content\": [\n                \"Допустимые значения: \",\n                {\n                    \"block\": \"inline-code\",\n                    \"content\": \"'auto'\"\n                },\n                \".\"\n            ]\n        },\n        {\n            \"block\": \"paragraph\",\n            \"content\": [\n                \"Способ использования: \",\n                {\n                    \"block\": \"inline-code\",\n                    \"content\": \"JS\"\n                },\n                \".\"\n            ]\n        },\n        {\n            \"block\": \"paragraph\",\n            \"content\": [\n                \"Блок с модификатором \",\n                {\n                    \"block\": \"inline-code\",\n                    \"content\": \"start\"\n                },\n                \" в значении \",\n                {\n                    \"block\": \"inline-code\",\n                    \"content\": \"auto\"\n                },\n                \" используется для автоматического запуска генерации события \",\n                {\n                    \"href\": \"#fields-tick\",\n                    \"block\": \"link\",\n                    \"content\": \"tick\"\n                },\n                \". Событие начинает генерироваться в момент инициализации блока.\"\n            ]\n        }\n    ]\n}"},"en":{"name":"tick","examples":[],"description":"<h1 id=\"tick-1\"><a href=\"#tick-1\" class=\"anchor\"></a>tick</h1>\n<p>This block provides an object for working with a regularly generated <code>tick</code> event (to implement the polling pattern).</p>\n<h2 id=\"overview-12\"><a href=\"#overview-12\" class=\"anchor\"></a>Overview</h2>\n<h3 id=\"object-events-2\"><a href=\"#object-events-2\" class=\"anchor\"></a>Object events</h3>\n<div class=\"table-container\"><table>\n<thead>\n<tr>\n<th>Name</th>\n<th>Description</th>\n</tr>\n</thead>\n<tbody>\n<tr>\n<td><a href=\"#events-tick\">tick</a></td>\n<td>A regularly generated event.</td>\n</tr>\n</tbody>\n</table>\n</div><h3 id=\"properties-and-methods-of-the-object-8\"><a href=\"#properties-and-methods-of-the-object-8\" class=\"anchor\"></a>Properties and methods of the object</h3>\n<div class=\"table-container\"><table>\n<thead>\n<tr>\n<th>Name</th>\n<th>Return type</th>\n<th>Description</th>\n</tr>\n</thead>\n<tbody>\n<tr>\n<td><a href=\"#fields-start\">start</a>()</td>\n<td>-</td>\n<td>Starts generating <code>tick</code> events if the process hasn&#39;t started yet.</td>\n</tr>\n<tr>\n<td><a href=\"#fields-stop\">stop</a>()</td>\n<td>-</td>\n<td>Stops generating <code>tick</code> events if the process hasn&#39;t stopped yet.</td>\n</tr>\n</tbody>\n</table>\n</div><h3 id=\"block-modifiers-4\"><a href=\"#block-modifiers-4\" class=\"anchor\"></a>Block modifiers</h3>\n<div class=\"table-container\"><table>\n<thead>\n<tr>\n<th>Modifier</th>\n<th>Acceptable values</th>\n<th>Usage</th>\n<th>Description</th>\n</tr>\n</thead>\n<tbody>\n<tr>\n<td><a href=\"#modifiers-start\">start</a></td>\n<td><code>&#39;auto&#39;</code></td>\n<td><code>JS</code></td>\n<td>Automatically starts generating events</td>\n</tr>\n</tbody>\n</table>\n</div><h3 id=\"public-block-technologies-15\"><a href=\"#public-block-technologies-15\" class=\"anchor\"></a>Public block technologies</h3>\n<p>The block is implemented in:</p>\n<ul>\n<li><code>vanilla.js</code></li>\n</ul>\n<h2 id=\"description-11\"><a href=\"#description-11\" class=\"anchor\"></a>Description</h2>\n<p><a name=\"events\"></a></p>\n<h3 id=\"object-events-3\"><a href=\"#object-events-3\" class=\"anchor\"></a>Object events</h3>\n<p><a name=\"events-tick\"></a></p>\n<h4 id=\"tick-event\"><a href=\"#tick-event\" class=\"anchor\"></a><code>tick</code> event</h4>\n<p>Subscribe to the event to use it to implement the polling pattern.</p>\n<p>An event is generated every 50 milliseconds.</p>\n<p><a name=\"fields\"></a></p>\n<h3 id=\"properties-and-methods-of-the-object-9\"><a href=\"#properties-and-methods-of-the-object-9\" class=\"anchor\"></a>Properties and methods of the object</h3>\n<p>The block is a descendant of the <code>Emitter</code> class in the <code>events</code> block, which allows it to call these classes.</p>\n<pre><code class=\"lang-js\">modules.require(&#39;tick&#39;, function(tick) {\n\nvar update = function() { /* ... */ };\n\ntick\n    .on(&#39;tick&#39;, update) // subscribing to the tick event\n    .start(); // starting generation of tick events\n});\n</code></pre>\n<p><a name=\"fields-start\"></a></p>\n<h4 id=\"start-method-1\"><a href=\"#start-method-1\" class=\"anchor\"></a><code>start</code> method</h4>\n<p>Starts generating <a href=\"#fields-tick\">tick</a> events if the process hasn&#39;t started yet. A <code>tick</code> is generated with an interval of 50 milliseconds after invoking the method.</p>\n<p>Doesn&#39;t accept arguments.</p>\n<p>No return value.</p>\n<p><a name=\"fields-stop\"></a></p>\n<h4 id=\"stop-method-1\"><a href=\"#stop-method-1\" class=\"anchor\"></a><code>stop</code> method</h4>\n<p>Stops generating <a href=\"#fields-tick\">tick</a> events.</p>\n<p>Doesn&#39;t accept arguments.</p>\n<p>No return value.</p>\n<p><a name=\"modifiers\"></a></p>\n<h3 id=\"block-modifiers-5\"><a href=\"#block-modifiers-5\" class=\"anchor\"></a>Block modifiers</h3>\n<p><a name=\"modifiers-start\"></a></p>\n<h4 id=\"start-modifier-1\"><a href=\"#start-modifier-1\" class=\"anchor\"></a><code>start</code> modifier</h4>\n<p>Acceptable values: <code>&#39;auto&#39;</code>.</p>\n<p>Usage: <code>JS</code>.</p>\n<p>Use the block with the <code>start</code> modifier set to <code>auto</code> in order to automatically start generating <a href=\"#fields-tick\">tick</a> events. The event starts being generated at the time of block initialization.</p>\n","bemjsonDescription":"{\n    \"block\": \"md-root\",\n    \"content\": [\n        {\n            \"level\": 1,\n            \"block\": \"heading\",\n            \"mods\": {\n                \"level\": 1\n            },\n            \"content\": \"tick\"\n        },\n        {\n            \"block\": \"paragraph\",\n            \"content\": [\n                \"This block provides an object for working with a regularly generated \",\n                {\n                    \"block\": \"inline-code\",\n                    \"content\": \"tick\"\n                },\n                \" event (to implement the polling pattern).\"\n            ]\n        },\n        {\n            \"level\": 2,\n            \"block\": \"heading\",\n            \"mods\": {\n                \"level\": 2\n            },\n            \"content\": \"Overview\"\n        },\n        {\n            \"level\": 3,\n            \"block\": \"heading\",\n            \"mods\": {\n                \"level\": 3\n            },\n            \"content\": \"Object events\"\n        },\n        {\n            \"align\": [\n                null,\n                null\n            ],\n            \"block\": \"table\",\n            \"rows\": [\n                [\n                    \"Name\",\n                    \"Description\"\n                ],\n                [\n                    [\n                        {\n                            \"block\": \"html\",\n                            \"content\": \"<a href=\\\"#events-tick\\\">\"\n                        },\n                        \"tick\",\n                        {\n                            \"block\": \"html\",\n                            \"content\": \"</a>\"\n                        }\n                    ],\n                    \"A regularly generated event.\"\n                ]\n            ]\n        },\n        {\n            \"level\": 3,\n            \"block\": \"heading\",\n            \"mods\": {\n                \"level\": 3\n            },\n            \"content\": \"Properties and methods of the object\"\n        },\n        {\n            \"align\": [\n                null,\n                null,\n                null\n            ],\n            \"block\": \"table\",\n            \"rows\": [\n                [\n                    \"Name\",\n                    \"Return type\",\n                    \"Description\"\n                ],\n                [\n                    [\n                        {\n                            \"block\": \"html\",\n                            \"content\": \"<a href=\\\"#fields-start\\\">\"\n                        },\n                        \"start\",\n                        {\n                            \"block\": \"html\",\n                            \"content\": \"</a>\"\n                        },\n                        \"()\"\n                    ],\n                    \"-\",\n                    [\n                        \"Starts generating \",\n                        {\n                            \"block\": \"inline-code\",\n                            \"content\": \"tick\"\n                        },\n                        \" events if the process hasn't started yet.\"\n                    ]\n                ],\n                [\n                    [\n                        {\n                            \"block\": \"html\",\n                            \"content\": \"<a href=\\\"#fields-stop\\\">\"\n                        },\n                        \"stop\",\n                        {\n                            \"block\": \"html\",\n                            \"content\": \"</a>\"\n                        },\n                        \"()\"\n                    ],\n                    \"-\",\n                    [\n                        \"Stops generating \",\n                        {\n                            \"block\": \"inline-code\",\n                            \"content\": \"tick\"\n                        },\n                        \" events if the process hasn't stopped yet.\"\n                    ]\n                ]\n            ]\n        },\n        {\n            \"level\": 3,\n            \"block\": \"heading\",\n            \"mods\": {\n                \"level\": 3\n            },\n            \"content\": \"Block modifiers\"\n        },\n        {\n            \"align\": [\n                null,\n                null,\n                null,\n                null\n            ],\n            \"block\": \"table\",\n            \"rows\": [\n                [\n                    \"Modifier\",\n                    \"Acceptable values\",\n                    \"Usage\",\n                    \"Description\"\n                ],\n                [\n                    [\n                        {\n                            \"block\": \"html\",\n                            \"content\": \"<a href=\\\"#modifiers-start\\\">\"\n                        },\n                        \"start\",\n                        {\n                            \"block\": \"html\",\n                            \"content\": \"</a>\"\n                        }\n                    ],\n                    {\n                        \"block\": \"inline-code\",\n                        \"content\": \"'auto'\"\n                    },\n                    {\n                        \"block\": \"inline-code\",\n                        \"content\": \"JS\"\n                    },\n                    \"Automatically starts generating events\"\n                ]\n            ]\n        },\n        {\n            \"level\": 3,\n            \"block\": \"heading\",\n            \"mods\": {\n                \"level\": 3\n            },\n            \"content\": \"Public block technologies\"\n        },\n        {\n            \"block\": \"paragraph\",\n            \"content\": \"The block is implemented in:\"\n        },\n        {\n            \"ordered\": false,\n            \"loose\": false,\n            \"block\": \"list\",\n            \"content\": {\n                \"loose\": false,\n                \"checked\": null,\n                \"block\": \"list-item\",\n                \"content\": {\n                    \"block\": \"paragraph\",\n                    \"content\": {\n                        \"block\": \"inline-code\",\n                        \"content\": \"vanilla.js\"\n                    }\n                }\n            }\n        },\n        {\n            \"level\": 2,\n            \"block\": \"heading\",\n            \"mods\": {\n                \"level\": 2\n            },\n            \"content\": \"Description\"\n        },\n        {\n            \"block\": \"paragraph\",\n            \"content\": [\n                {\n                    \"block\": \"html\",\n                    \"content\": \"<a name=\\\"events\\\">\"\n                },\n                {\n                    \"block\": \"html\",\n                    \"content\": \"</a>\"\n                }\n            ]\n        },\n        {\n            \"level\": 3,\n            \"block\": \"heading\",\n            \"mods\": {\n                \"level\": 3\n            },\n            \"content\": \"Object events\"\n        },\n        {\n            \"block\": \"paragraph\",\n            \"content\": [\n                {\n                    \"block\": \"html\",\n                    \"content\": \"<a name=\\\"events-tick\\\">\"\n                },\n                {\n                    \"block\": \"html\",\n                    \"content\": \"</a>\"\n                }\n            ]\n        },\n        {\n            \"level\": 4,\n            \"block\": \"heading\",\n            \"mods\": {\n                \"level\": 4\n            },\n            \"content\": [\n                {\n                    \"block\": \"inline-code\",\n                    \"content\": \"tick\"\n                },\n                \" event\"\n            ]\n        },\n        {\n            \"block\": \"paragraph\",\n            \"content\": \"Subscribe to the event to use it to implement the polling pattern.\"\n        },\n        {\n            \"block\": \"paragraph\",\n            \"content\": \"An event is generated every 50 milliseconds.\"\n        },\n        {\n            \"block\": \"paragraph\",\n            \"content\": [\n                {\n                    \"block\": \"html\",\n                    \"content\": \"<a name=\\\"fields\\\">\"\n                },\n                {\n                    \"block\": \"html\",\n                    \"content\": \"</a>\"\n                }\n            ]\n        },\n        {\n            \"level\": 3,\n            \"block\": \"heading\",\n            \"mods\": {\n                \"level\": 3\n            },\n            \"content\": \"Properties and methods of the object\"\n        },\n        {\n            \"block\": \"paragraph\",\n            \"content\": [\n                \"The block is a descendant of the \",\n                {\n                    \"block\": \"inline-code\",\n                    \"content\": \"Emitter\"\n                },\n                \" class in the \",\n                {\n                    \"block\": \"inline-code\",\n                    \"content\": \"events\"\n                },\n                \" block, which allows it to call these classes.\"\n            ]\n        },\n        {\n            \"lang\": \"js\",\n            \"block\": \"code\",\n            \"content\": \"modules.require('tick', function(tick) {\\n\\nvar update = function() { /* ... */ };\\n\\ntick\\n    .on('tick', update) // subscribing to the tick event\\n    .start(); // starting generation of tick events\\n});\\n\"\n        },\n        {\n            \"block\": \"paragraph\",\n            \"content\": [\n                {\n                    \"block\": \"html\",\n                    \"content\": \"<a name=\\\"fields-start\\\">\"\n                },\n                {\n                    \"block\": \"html\",\n                    \"content\": \"</a>\"\n                }\n            ]\n        },\n        {\n            \"level\": 4,\n            \"block\": \"heading\",\n            \"mods\": {\n                \"level\": 4\n            },\n            \"content\": [\n                {\n                    \"block\": \"inline-code\",\n                    \"content\": \"start\"\n                },\n                \" method\"\n            ]\n        },\n        {\n            \"block\": \"paragraph\",\n            \"content\": [\n                \"Starts generating \",\n                {\n                    \"href\": \"#fields-tick\",\n                    \"block\": \"link\",\n                    \"content\": \"tick\"\n                },\n                \" events if the process hasn't started yet. A \",\n                {\n                    \"block\": \"inline-code\",\n                    \"content\": \"tick\"\n                },\n                \" is generated with an interval of 50 milliseconds after invoking the method.\"\n            ]\n        },\n        {\n            \"block\": \"paragraph\",\n            \"content\": \"Doesn't accept arguments.\"\n        },\n        {\n            \"block\": \"paragraph\",\n            \"content\": \"No return value.\"\n        },\n        {\n            \"block\": \"paragraph\",\n            \"content\": [\n                {\n                    \"block\": \"html\",\n                    \"content\": \"<a name=\\\"fields-stop\\\">\"\n                },\n                {\n                    \"block\": \"html\",\n                    \"content\": \"</a>\"\n                }\n            ]\n        },\n        {\n            \"level\": 4,\n            \"block\": \"heading\",\n            \"mods\": {\n                \"level\": 4\n            },\n            \"content\": [\n                {\n                    \"block\": \"inline-code\",\n                    \"content\": \"stop\"\n                },\n                \" method\"\n            ]\n        },\n        {\n            \"block\": \"paragraph\",\n            \"content\": [\n                \"Stops generating \",\n                {\n                    \"href\": \"#fields-tick\",\n                    \"block\": \"link\",\n                    \"content\": \"tick\"\n                },\n                \" events.\"\n            ]\n        },\n        {\n            \"block\": \"paragraph\",\n            \"content\": \"Doesn't accept arguments.\"\n        },\n        {\n            \"block\": \"paragraph\",\n            \"content\": \"No return value.\"\n        },\n        {\n            \"block\": \"paragraph\",\n            \"content\": [\n                {\n                    \"block\": \"html\",\n                    \"content\": \"<a name=\\\"modifiers\\\">\"\n                },\n                {\n                    \"block\": \"html\",\n                    \"content\": \"</a>\"\n                }\n            ]\n        },\n        {\n            \"level\": 3,\n            \"block\": \"heading\",\n            \"mods\": {\n                \"level\": 3\n            },\n            \"content\": \"Block modifiers\"\n        },\n        {\n            \"block\": \"paragraph\",\n            \"content\": [\n                {\n                    \"block\": \"html\",\n                    \"content\": \"<a name=\\\"modifiers-start\\\">\"\n                },\n                {\n                    \"block\": \"html\",\n                    \"content\": \"</a>\"\n                }\n            ]\n        },\n        {\n            \"level\": 4,\n            \"block\": \"heading\",\n            \"mods\": {\n                \"level\": 4\n            },\n            \"content\": [\n                {\n                    \"block\": \"inline-code\",\n                    \"content\": \"start\"\n                },\n                \" modifier\"\n            ]\n        },\n        {\n            \"block\": \"paragraph\",\n            \"content\": [\n                \"Acceptable values: \",\n                {\n                    \"block\": \"inline-code\",\n                    \"content\": \"'auto'\"\n                },\n                \".\"\n            ]\n        },\n        {\n            \"block\": \"paragraph\",\n            \"content\": [\n                \"Usage: \",\n                {\n                    \"block\": \"inline-code\",\n                    \"content\": \"JS\"\n                },\n                \".\"\n            ]\n        },\n        {\n            \"block\": \"paragraph\",\n            \"content\": [\n                \"Use the block with the \",\n                {\n                    \"block\": \"inline-code\",\n                    \"content\": \"start\"\n                },\n                \" modifier set to \",\n                {\n                    \"block\": \"inline-code\",\n                    \"content\": \"auto\"\n                },\n                \" in order to automatically start generating \",\n                {\n                    \"href\": \"#fields-tick\",\n                    \"block\": \"link\",\n                    \"content\": \"tick\"\n                },\n                \" events. The event starts being generated at the time of block initialization.\"\n            ]\n        }\n    ]\n}"}}